fiftyone_devicedetection_cloud/__init__.py
fiftyone_devicedetection_cloud/devicedetection_cloud.py
fiftyone_devicedetection_cloud/devicedetection_cloud_pipelinebuilder.py
fiftyone_devicedetection_cloud/hardwareprofile_cloud.py
fiftyone_devicedetection_cloud-4.5.18.dist-info/METADATA
fiftyone_devicedetection_cloud-4.5.18.dist-info/WHEEL
fiftyone_devicedetection_cloud-4.5.18.dist-info/top_level.txt
fiftyone_devicedetection_cloud-4.5.18.dist-info/RECORD
