Metadata-Version: 2.4
Name: fiftyone_devicedetection_cloud
Version: 4.5.18
Summary: 51Degrees Device Detection parses HTTP headers to return detailed hardware, operating system, browser, and crawler information for the devices used to access your website or service. This package retrieves device detection results by consuming the 51Degrees cloud service.
Home-page: https://51degrees.com/
Author: 51Degrees Engineering
Author-email: engineering@51degrees.com
License: EUPL-1.2
Classifier: Development Status :: 5 - Production/Stable
Classifier: Programming Language :: Python
Classifier: License :: OSI Approved :: European Union Public Licence 1.2 (EUPL 1.2)
Classifier: Operating System :: OS Independent
Classifier: Topic :: Software Development :: Libraries :: Python Modules
Requires-Python: >=3.8
Requires-Dist: fiftyone_devicedetection_shared
Dynamic: author
Dynamic: author-email
Dynamic: classifier
Dynamic: description
Dynamic: description-content-type
Dynamic: home-page
Dynamic: license
Dynamic: requires-dist
Dynamic: requires-python
Dynamic: summary
